django_subjective_sort/__init__.py
django_subjective_sort/models.py
django_subjective_sort-1.0.1.dist-info/LICENSE
django_subjective_sort-1.0.1.dist-info/METADATA
django_subjective_sort-1.0.1.dist-info/WHEEL
django_subjective_sort-1.0.1.dist-info/top_level.txt
django_subjective_sort-1.0.1.dist-info/RECORD
