Metadata-Version: 2.1
Name: django-subjective-sort
Version: 1.0.1
Summary: Allows items of a collection to be manually sorted(such as for use with drag-and-drop).
Home-page: https://github.com/builtbykrit/django-subjective-sort
Author: Michael Prather
Author-email: michael@krit.com
Project-URL: Bug Tracker, https://github.com/builtbykrit/django-subjective-sort/issues
Classifier: Programming Language :: Python :: 3
Classifier: License :: OSI Approved :: MIT License
Classifier: Operating System :: OS Independent
Classifier: Framework :: Django :: 4.1
Classifier: Framework :: Django :: 4.0
Classifier: Framework :: Django :: 3.2
Requires-Python: >=3.9
License-File: LICENSE
